bio_wrangler/__init__.py
bio_wrangler/bio_wrangler.py
bio_wrangler/utils.py
bio_wrangler/tests/__init__.py
bio_wrangler/tests/test_biowrangler.py
bio_wrangler/tests/test_utils.py
bio_wrangler-0.2.dist-info/METADATA
bio_wrangler-0.2.dist-info/WHEEL
bio_wrangler-0.2.dist-info/top_level.txt
bio_wrangler-0.2.dist-info/RECORD
