Metadata-Version: 2.1
Name: bio-wrangler
Version: 0.2
Summary: A bioinformatics data wrangling package for FASTA, FASTQ, VCF, and GFF files.
Home-page: https://github.com/se7en69/bio-wrangler
Author: Abdul-Rehman ikram
Author-email: hanzo7n@gmail.com
License: MIT
Project-URL: Bug Tracker, https://github.com/se7en69/bio-wrangler/issues
Classifier: Programming Language :: Python :: 3
Classifier: License :: OSI Approved :: MIT License
Classifier: Operating System :: OS Independent
Requires-Python: >=3.6
Requires-Dist: pandas
Requires-Dist: biopython
Requires-Dist: gffutils
Requires-Dist: pyvcf3
